virtualprototype/modules/gpio/verilog/gpio.v
`define HI 1'b1         // Define TRUE as a 1-bit value of 1
`define LO 1'b0        // Define FALSE as a 1-bit value of 0


module gpio #(parameter        nrOfInputs = 8,
              parameter        nrOfOutputs = 8,
              parameter [31:0] Base = 32'h40000000)
            ( input wire                    clock,
                                            reset,

              input wire [nrOfInputs-1:0]   externalInputs,
              output wire [nrOfOutputs-1:0] externalOutputs,

              // here the bus interface is defined
              input wire         beginTransactionIn,
                                 endTransactionIn,
                                 readNotWriteIn,

                                 dataValidIn,
                                 busErrorIn,
                                 busyIn,

              input wire [31:0]  addressDataIn,
              input wire [3:0]   byteEnablesIn,
              input wire [7:0]   burstSizeIn,

              output wire        endTransactionOut,
                                 dataValidOut,
                                 busErrorOut,
              output wire [31:0] addressDataOut);

  //===========================================================================
  // Regs
  //===========================================================================

  reg        s_beginTransactionReg, s_transactionActiveReg, s_readNotWriteReg;
  reg [31:2] s_addressDataInReg;
  reg [3:0]  s_byteEnablesReg;
  reg [7:0]  s_burstSizeReg;

  reg [nrOfOutputs-1:0] s_externalOutputsReg;

  reg [nrOfInputs-1:0] s_externalInputsReg;
  reg s_dataValidOutReg, s_endTransReg;
  reg [31:0] s_addressDataOutReg;

  //===========================================================================
  // Wires
  //===========================================================================

  wire s_isMyAction;      
  wire s_isCorrectAction; 
  wire s_isWriteAction;   
  wire s_isReadAction;    

  //–––––––––––––––––––––––––––––––––––––––––––––––––––––––––––––––––––––––––––––––––––––––––––––––––––––––––––––––––––––
  // Here we flipflop all bus signals and determine the control and error signals
  //–––––––––––––––––––––––––––––––––––––––––––––––––––––––––––––––––––––––––––––––––––––––––––––––––––––––––––––––––––––


  assign s_isMyAction      = (s_addressDataInReg == Base[31:2]) ? s_transactionActiveReg : `LO;
  assign s_isCorrectAction = (s_byteEnablesReg == 4'hF && s_burstSizeReg == 8'd0) ? s_isMyAction : `LO;
  assign s_isWriteAction   = s_isMyAction & s_isCorrectAction & ~s_readNotWriteReg;
  assign s_isReadAction    = s_isMyAction & s_isCorrectAction & s_readNotWriteReg;
  
  assign busErrorOut = s_isMyAction & ~s_isCorrectAction;

  always @(posedge clock)
    begin

      s_beginTransactionReg <= beginTransactionIn;

      if (reset == `HI || endTransactionIn == `HI)  s_transactionActiveReg <= `LO;
      else if (beginTransactionIn == `HI)           s_transactionActiveReg <= `HI;

      if (beginTransactionIn == `HI) 
        s_readNotWriteReg   <= readNotWriteIn;
        s_addressDataInReg  <= addressDataIn[31:2];
        s_byteEnablesReg    <= byteEnablesIn;
        s_burstSizeReg      <= burstSizeIn;

    end
  
  //–––––––––––––––––––––––––––––––––––––––––––––––––––––––––––––––––––––––––––––––––––––––––––––––––––––––––––––––––––––
  // Here we define the write action 
  //–––––––––––––––––––––––––––––––––––––––––––––––––––––––––––––––––––––––––––––––––––––––––––––––––––––––––––––––––––––
   
  assign externalOutputs = s_externalOutputsReg;
  always @(posedge clock)

    if (reset == `HI)             
      s_externalOutputsReg <= {nrOfOutputs{`LO}};

    else if ( s_isWriteAction == `HI && dataValidIn == `HI)       
      s_externalOutputsReg <= addressDataIn[nrOfOutputs-1:0];

    else
      s_externalOutputsReg <= s_externalOutputsReg;

  //–––––––––––––––––––––––––––––––––––––––––––––––––––––––––––––––––––––––––––––––––––––––––––––––––––––––––––––––––––––
  //Here we define the read action
  //–––––––––––––––––––––––––––––––––––––––––––––––––––––––––––––––––––––––––––––––––––––––––––––––––––––––––––––––––––––
  
  
  assign dataValidOut      = s_dataValidOutReg;
  assign endTransactionOut = s_endTransReg;
  assign addressDataOut    = s_addressDataOutReg;
  
  always @(posedge clock) 
    begin
      s_externalInputsReg <= externalInputs;

      if (reset == `HI) begin
        s_dataValidOutReg <= `LO;
        s_addressDataOutReg <= 32'd0;

      end else if ( s_isReadAction == `HI && s_beginTransactionReg == `HI) begin
        s_dataValidOutReg <= `HI;
        s_addressDataOutReg <= { {(32-nrOfOutputs){`LO}} , s_externalInputsReg };

      end else if (busyIn == `LO) begin
        s_dataValidOutReg <= `LO;
        s_addressDataOutReg <= 32'd0;

      end

      s_endTransReg <= s_dataValidOutReg & ~busyIn;
    end    
    
               
endmodule

virtualprototype/modules/gpio/verilog/gpio_tb.v
`timescale 1ns / 1ps

`define HI 1'b1
`define LO 1'b0

module gpio_tb;

  // Parameters
  localparam nrOfInputs  = 8;
  localparam nrOfOutputs = 8;
  localparam [31:0] Base = 32'h40000000;

  // Signals
  reg clock, reset;
  reg [nrOfInputs-1:0] externalInputs;
  wire [nrOfOutputs-1:0] externalOutputs;

  reg beginTransactionIn, endTransactionIn, readNotWriteIn;
  reg dataValidIn, busErrorIn, busyIn;
  reg [31:0] addressDataIn;
  reg [3:0] byteEnablesIn;
  reg [7:0] burstSizeIn;

  wire endTransactionOut, dataValidOut, busErrorOut;
  wire [31:0] addressDataOut;

  // Instantiate DUT
  gpio #(
    .nrOfInputs(nrOfInputs),
    .nrOfOutputs(nrOfOutputs),
    .Base(Base)
  ) uut (
    .clock(clock),
    .reset(reset),
    .externalInputs(externalInputs),
    .externalOutputs(externalOutputs),
    .beginTransactionIn(beginTransactionIn),
    .endTransactionIn(endTransactionIn),
    .readNotWriteIn(readNotWriteIn),
    .dataValidIn(dataValidIn),
    .busErrorIn(busErrorIn),
    .busyIn(busyIn),
    .addressDataIn(addressDataIn),
    .byteEnablesIn(byteEnablesIn),
    .burstSizeIn(burstSizeIn),
    .endTransactionOut(endTransactionOut),
    .dataValidOut(dataValidOut),
    .busErrorOut(busErrorOut),
    .addressDataOut(addressDataOut)
  );

  // Clock generation
  always #5 clock = ~clock;

  // Simulation
  initial begin
    $dumpfile("gpio.vcd");
    $dumpvars(0, gpio_tb);

    // Initialization
    clock = 0;
    reset = `HI;
    beginTransactionIn = `LO;
    endTransactionIn = `LO;
    readNotWriteIn = `LO;
    dataValidIn = `LO;
    busErrorIn = `LO;
    busyIn = `LO;
    addressDataIn = 32'd0;
    byteEnablesIn = 4'h0;
    burstSizeIn = 8'd0;
    externalInputs = 8'hA5;

    #20 reset = `LO;

    // ─────────────────────────────────────────────
    // 1. Shortest Read Transaction
    // ─────────────────────────────────────────────
    #50;
    addressDataIn = Base;
    byteEnablesIn = 4'hF;
    burstSizeIn = 8'd0;
    readNotWriteIn = `HI;
    beginTransactionIn = `HI;
    #10 beginTransactionIn = `LO;
    #20;

    // ─────────────────────────────────────────────
    // 2. General Read Transaction with busy delay
    // ─────────────────────────────────────────────
    #50;
    addressDataIn = Base;
    byteEnablesIn = 4'hF;
    burstSizeIn = 8'd0;
    readNotWriteIn = `HI;
    beginTransactionIn = `HI;
    #10 beginTransactionIn = `LO;
    busyIn = `HI;
    #20 busyIn = `LO;

    // ─────────────────────────────────────────────
    // 3. Write Transaction
    // ─────────────────────────────────────────────
    #50;
    addressDataIn = {Base[31:2], 2'b00} | 32'h000000A5; // Write value A5
    byteEnablesIn = 4'hF;
    burstSizeIn = 8'd0;
    readNotWriteIn = `LO;
    beginTransactionIn = `HI;
    #10 beginTransactionIn = `LO;
    dataValidIn = `HI;
    #10 dataValidIn = `LO;

    // ─────────────────────────────────────────────
    // 4. Busy Extended Write Transaction
    // ─────────────────────────────────────────────
    #50;
    addressDataIn = {Base[31:2], 2'b00} | 32'h0000005A; // Write value 5A
    byteEnablesIn = 4'hF;
    burstSizeIn = 8'd0;
    readNotWriteIn = `LO;
    beginTransactionIn = `HI;
    #10 beginTransactionIn = `LO;
    dataValidIn = `HI;
    busyIn = `HI;
    #20 busyIn = `LO;
    dataValidIn = `LO;

    #50;
    $display("Final externalOutputs = %h", externalOutputs);
    $display("Final addressDataOut  = %h", addressDataOut);

    $finish;
  end

endmodule

virtualprototype/modules/gpio/verilog/gpio.vcd
$date
	Sat May 17 16:28:40 2025
$end
$version
	Icarus Verilog
$end
$timescale
	1ps
$end
$scope module gpio_tb $end
$var wire 8 ! externalOutputs [7:0] $end
$var wire 1 " endTransactionOut $end
$var wire 1 # dataValidOut $end
$var wire 1 $ busErrorOut $end
$var wire 32 % addressDataOut [31:0] $end
$var parameter 32 & Base $end
$var parameter 32 ' nrOfInputs $end
$var parameter 32 ( nrOfOutputs $end
$var reg 32 ) addressDataIn [31:0] $end
$var reg 1 * beginTransactionIn $end
$var reg 8 + burstSizeIn [7:0] $end
$var reg 1 , busErrorIn $end
$var reg 1 - busyIn $end
$var reg 4 . byteEnablesIn [3:0] $end
$var reg 1 / clock $end
$var reg 1 0 dataValidIn $end
$var reg 1 1 endTransactionIn $end
$var reg 8 2 externalInputs [7:0] $end
$var reg 1 3 readNotWriteIn $end
$var reg 1 4 reset $end
$scope module uut $end
$var wire 32 5 addressDataIn [31:0] $end
$var wire 32 6 addressDataOut [31:0] $end
$var wire 1 * beginTransactionIn $end
$var wire 8 7 burstSizeIn [7:0] $end
$var wire 1 , busErrorIn $end
$var wire 1 $ busErrorOut $end
$var wire 1 - busyIn $end
$var wire 4 8 byteEnablesIn [3:0] $end
$var wire 1 / clock $end
$var wire 1 0 dataValidIn $end
$var wire 1 # dataValidOut $end
$var wire 1 1 endTransactionIn $end
$var wire 1 " endTransactionOut $end
$var wire 8 9 externalInputs [7:0] $end
$var wire 8 : externalOutputs [7:0] $end
$var wire 1 3 readNotWriteIn $end
$var wire 1 4 reset $end
$var wire 1 ; s_isReadAction $end
$var wire 1 < s_isWriteAction $end
$var wire 1 = s_isMyAction $end
$var wire 1 > s_isCorrectAction $end
$var parameter 32 ? Base $end
$var parameter 32 @ nrOfInputs $end
$var parameter 32 A nrOfOutputs $end
$var reg 30 B s_addressDataInReg [31:2] $end
$var reg 32 C s_addressDataOutReg [31:0] $end
$var reg 1 D s_beginTransactionReg $end
$var reg 8 E s_burstSizeReg [7:0] $end
$var reg 4 F s_byteEnablesReg [3:0] $end
$var reg 1 G s_dataValidOutReg $end
$var reg 1 H s_endTransReg $end
$var reg 8 I s_externalInputsReg [7:0] $end
$var reg 8 J s_externalOutputsReg [7:0] $end
$var reg 1 K s_readNotWriteReg $end
$var reg 1 L s_transactionActiveReg $end
$upscope $end
$upscope $end
$enddefinitions $end
$comment Show the parameter values. $end
$dumpall
b1000 A
b1000 @
b1000000000000000000000000000000 ?
b1000 (
b1000 '
b1000000000000000000000000000000 &
$end
#0
$dumpvars
xL
xK
bx J
bx I
xH
xG
bx F
bx E
xD
bx C
bx B
x>
x=
x<
x;
bx :
b10100101 9
b0 8
b0 7
bx 6
b0 5
14
03
b10100101 2
01
00
0/
b0 .
0-
0,
b0 +
0*
b0 )
bx %
x$
x#
x"
bx !
$end
#5000
0;
0<
0>
0$
0=
b0 E
b0 F
b0 B
0L
0D
b0 !
b0 :
b0 J
b0 %
b0 6
b0 C
0#
0G
b10100101 I
1/
#10000
0/
#15000
0"
0H
1/
#20000
0/
04
#25000
1/
#30000
0/
#35000
1/
#40000
0/
#45000
1/
#50000
0/
#55000
1/
#60000
0/
#65000
1/
#70000
0/
1*
13
b1111 .
b1111 8
b1000000000000000000000000000000 )
b1000000000000000000000000000000 5
#75000
1;
1>
0$
1=
b1111 F
b10000000000000000000000000000 B
1K
1L
1D
1/
#80000
0/
0*
#85000
0D
b10100101 %
b10100101 6
b10100101 C
1#
1G
1/
#90000
0/
#95000
1"
1H
b0 %
b0 6
b0 C
0#
0G
1/
#100000
0/
#105000
0"
0H
1/
#110000
0/
#115000
1/
#120000
0/
#125000
1/
#130000
0/
#135000
1/
#140000
0/
#145000
1/
#150000
0/
1*
#155000
1D
1/
#160000
0/
1-
0*
#165000
0D
b10100101 %
b10100101 6
b10100101 C
1#
1G
1/
#170000
0/
#175000
1/
#180000
0/
0-
#185000
1"
1H
b0 %
b0 6
b0 C
0#
0G
1/
#190000
0/
#195000
0"
0H
1/
#200000
0/
#205000
1/
#210000
0/
#215000
1/
#220000
0/
#225000
1/
#230000
0/
1*
03
b1000000000000000000000010100101 )
b1000000000000000000000010100101 5
#235000
0>
0<
0=
0;
b10000000000000000000000101001 B
0K
1D
1/
#240000
0/
10
0*
#245000
0D
1/
#250000
0/
00
#255000
1/
#260000
0/
#265000
1/
#270000
0/
#275000
1/
#280000
0/
#285000
1/
#290000
0/
#295000
1/
#300000
0/
1*
b1000000000000000000000001011010 )
b1000000000000000000000001011010 5
#305000
b10000000000000000000000010110 B
1D
1/
#310000
0/
1-
10
0*
#315000
0D
1/
#320000
0/
#325000
1/
#330000
0/
00
0-
