virtualprototype/modules/myMemory/verilog/_mySSRAM.v
`define HI 1'b1
`define LO 1'b0


module _mySSRAM #(parameter                               bitwidth = 8,
                  parameter                               nrOfEntries = 512)
                 (input wire                              clockA, 
                                                          clockB,
                                                          writeEnableA, 
                                                          writeEnableB,
                  input wire [$clog2(nrOfEntries)-1 : 0]  addressA, 
                                                          addressB,
                  input wire [bitwidth-1 : 0]             dataInA, 
                                                          dataInB,
                  output reg [bitwidth-1 : 0]             dataOutA, 
                                                          dataOutB);


  // Memory content declaration
  reg [bitwidth-1 : 0] memoryContent [nrOfEntries-1 : 0];

  //=============================================================
  // Port A (clockA domain): Read/Write Logic
  always @(posedge clockA) begin
    
    if (writeEnableA == `HI) memoryContent[addressA] <= dataInA;

    dataOutA <= memoryContent[addressA];

  end

  // Port B (clockB domain): Read/Write Logic
  always @(posedge clockB) begin

    if (writeEnableB == `HI) memoryContent[addressB] <= dataInB;

    dataOutB <= memoryContent[addressB];

  end

endmodule

virtualprototype/modules/myMemory/verilog/myDmaRamCI.v
`define HI     1'b1  
`define LO     1'b0
`define LO_4   4'b0
`define LO_8   8'b0
`define LO_10 10'b0
`define LO_22 22'b0
`define LO_30 30'b0
`define LO_32 32'b0



module myDmaRam #( parameter [7:0]    customId = 8'h14 )
                 ( input wire         start,
                                      clock,
                                      reset,
                                      
                   input wire [31:0]  valueA, // Address
                                      valueB, // Data
                   input wire [7:0]   ciN,
                   output wire        done,
                   output wire [31:0] result,

                   // Bus interface signals
                   output wire        requestTransaction,
                   input wire         transactionGranted,
                   input wire         endTransactionIn,
                                      dataValidIn,
                                      busErrorIn,
                                      busyIn,
                   input wire [31:0]  addressDataIn,
                   output reg         beginTransactionOut,
                   output reg         readNotWriteOut,
                   output reg [3:0]   byteEnablesOut,
                   output reg [7:0]   burstSizeOut,
                   output reg [31:0]  addressDataOut );

  //===============================================================================================
  // Local parameters for internal constants
  //===============================================================================================

  // Address bit ranges for various purposes
  localparam       CF_HI_B            = 12, // High bit for DMA configuration field in address
                   CF_LO_B            = 10, // High bit for DMA configuration field in address
                   WRITE_B            = 9;  // Bit position indicating write operation in address
  // Localparam for read register selection - defines which register is accessed
  localparam [2:0] MEM_DATA           = 3'b000,
                   BUS_START_ADDR     = 3'b001,
                   MEM_START_ADDR     = 3'b010,
                   BLOCK_SIZE         = 3'b011,
                   BURST_SIZE         = 3'b100,
                   STATUS_R           = 3'b101;

  // DMA controller FSM states (3-bit encoding)
  localparam [2:0] IDLE               = 3'd0,
                   INIT               = 3'd1,
                   REQUEST_BUS        = 3'd2,
                   SET_UP_TRANS       = 3'd3,
                   DO_READ            = 3'd4,
                   WAIT_END           = 3'd5;

  // Control bits for DMA direction
  localparam [1:0] START_BUS_TO_MEM   = 2'b01, // Start DMA from bus to memory
                   START_MEM_TO_BUT   = 2'b10; // Start DMA from memory to bus (likely typo 'BUT' means 'BUS')
  localparam       DMA_HI_B           = 1,    // High bit position for control bits
                   DMA_LO_B           = 0;    // Low bit position for control bits
  // Constants for address and burst increments
  localparam [31:0]ADDR_BYTE_INC      = 32'd4;  // Byte increment for address (32-bit word)
  localparam [8:0] ADDR_RAM_INC       = 9'd1;   // RAM address increment (1)
  localparam [9:0] SINGLE_BLOCK       = 10'd1;  // Single block size (1)
  localparam [3:0] BYTE_HI_ALL        = 4'b1111; // Byte enables all high (all bytes enabled)
  
  //=============================================================
  // Internal wires and registers
  //=============================================================
  reg  [31:0] r_busStartAddr,      r_memoryStartAddr,  r_blockSize,         r_usedBurstSize;
  reg  [31:0] r_AddrDataIn,        r_result,           r_busStartAddrShad;
  reg  [9:0]  r_blockSizeShad;
  reg  [8:0]  r_ramCiAddr;
  reg  [2:0]  r_dmaState,          r_dmaNextState;
  reg         r_busError,          r_isSramRead,        r_endTransIn,       r_dataValidIn;

  wire [31:0] s_sramDataValue;
  wire [8:0]  s_dmaAddrCI;
  wire [7:0]  s_usedBurstSize;
  wire [2:0]  s_dmaConfig;
  wire        s_dmaDone,            s_isMyCi,            s_isSramWrite,       s_dmaWrite,         
              s_dmaIsAddrLO,        s_requestDmaIn,      s_ramCiWriteEnable,  s_transCompleted;

  //–––––––––––––––––––––––––––––––––––––––––––––––––––––––––––––––––––––––––––––––––––––––––––––––––––––––––––––––––––––
  //–––––––––––––––––––––––––––––––––––––––––––––––––––––––––––––––––––––––––––––––––––––––––––––––––––––––––––––––––––––
  // Assigns
  //–––––––––––––––––––––––––––––––––––––––––––––––––––––––––––––––––––––––––––––––––––––––––––––––––––––––––––––––––––––
  //–––––––––––––––––––––––––––––––––––––––––––––––––––––––––––––––––––––––––––––––––––––––––––––––––––––––––––––––––––––
  assign s_dmaConfig      = valueA[CF_HI_B:CF_LO_B];           // Extract DMA configuration field from valueA (bits 12:10)
  assign s_dmaWrite       = valueA[WRITE_B];                   // Write operation flag from valueA (bit 9)
  assign s_dmaAddrCI      = valueA[8:0];                       // Address for custom instruction SRAM access (bits 8:0)
  assign s_dmaIsAddrLO    = (valueA[31:CF_HI_B+1] == `LO_22);  // Check if address bits [31:10] are all zero (indicates local access)

  assign result           = r_result;                          // Output result register to result port

  //=============================================================
  // CI Logic
  //=============================================================

  assign s_isMyCi       = start && (ciN == customId);
  assign s_isSramWrite  = s_dmaIsAddrLO && s_isMyCi && s_dmaWrite;
  assign done           = (s_isMyCi & s_dmaWrite) | r_isSramRead;


  // Read request for custom instruction interface
  always @(posedge clock) 
      if (reset)         begin r_isSramRead <= `LO;           end 
      else if (s_isMyCi) begin r_isSramRead <= (~s_isSramWrite); end

  // Configuration registers on write from custom instruction interface
  always @(posedge clock) begin
    if (reset) begin
                        r_busStartAddr    <= `LO_32;
                        r_memoryStartAddr <= `LO_32;
                        r_blockSize       <= `LO_32;
                        r_usedBurstSize   <= `LO_32;

    end else if (s_isSramWrite)
      case (s_dmaConfig)
        BUS_START_ADDR: r_busStartAddr         <= valueB;
        MEM_START_ADDR: r_memoryStartAddr[8:0] <= valueB[8:0];
        BLOCK_SIZE:     r_blockSize[9:0]       <= valueB[9:0];
        BURST_SIZE:     r_usedBurstSize[7:0]   <= valueB[7:0];
      endcase
  end

  // Result register based on readback selection
  always @*
    if (r_isSramRead)
      case (s_dmaConfig)
        MEM_DATA:         r_result <= s_sramDataValue;
        BUS_START_ADDR:   r_result <= r_busStartAddr;
        MEM_START_ADDR:   r_result <= r_memoryStartAddr;
        BLOCK_SIZE:       r_result <= r_blockSize;
        BURST_SIZE:       r_result <= r_usedBurstSize;
        STATUS_R:         r_result <= {`LO_30, r_busError, ~(r_dmaState == IDLE)};
        default:          r_result <= `LO_32;
      endcase
    else
      r_result <= `LO_32;

  //=============================================================
  // BUS Logic
  //=============================================================

  wire [7:0]  _maxBurstSize      = {2'd0, r_usedBurstSize[7:0]} + SINGLE_BLOCK; // Calculate the maximum burst size (used for burst transfers)
  wire [7:0]  _restingBlockSize  = r_blockSizeShad - SINGLE_BLOCK;              // Calculate the remaining block size after a burst
  assign      s_usedBurstSize    = (r_blockSizeShad > _maxBurstSize) ? r_usedBurstSize[7:0] : _restingBlockSize[7:0]; // Select the burst size to use for the current transaction

  assign      requestTransaction = (r_dmaState == REQUEST_BUS);                 // Assert requestTransaction when the DMA FSM is in the REQUEST_BUS state

  wire        _controlBits  = (valueB[DMA_HI_B:DMA_LO_B] == START_BUS_TO_MEM) || 
                              (valueB[DMA_HI_B:DMA_LO_B] == START_MEM_TO_BUT); // Check if control bits indicate a valid DMA direction

  assign      s_requestDmaIn     = (s_dmaConfig == STATUS_R) && s_isMyCi && valueB[0] && _controlBits; // Assert s_requestDmaIn when a valid DMA request is detected via CI
  assign      s_dmaDone          = (r_blockSizeShad == `LO_10) || ((r_blockSizeShad == SINGLE_BLOCK) && r_dataValidIn); // DMA done when all blocks are transferred or last block is completed
  assign      s_ramCiWriteEnable = (r_dmaState == DO_READ) && r_dataValidIn;   // Enable SRAM write from DMA when in DO_READ state and data is valid
  assign      s_transCompleted   = r_endTransIn && s_dmaDone;                  // Transaction is completed when endTransactionIn is asserted and DMA is done

  // Latch bus interface signals on each clock
  always @(posedge clock) begin
    r_endTransIn  <= endTransactionIn;
    r_dataValidIn <= dataValidIn;
    r_AddrDataIn  <= addressDataIn;
  end

  // Shadow registers for burst/block management and address incrementing
  always @(posedge clock) begin
    if (r_dmaState == IDLE) begin
      r_busStartAddrShad <= r_busStartAddr;
      r_blockSizeShad    <= r_blockSize[9:0];
      r_ramCiAddr        <= r_memoryStartAddr[8:0];

    end else if (s_ramCiWriteEnable) begin
      r_busStartAddrShad <= r_busStartAddrShad + ADDR_BYTE_INC;
      r_blockSizeShad    <= r_blockSizeShad - SINGLE_BLOCK;
      r_ramCiAddr        <= r_ramCiAddr + ADDR_RAM_INC;
    end
  end

  // Output bus transaction control signals based on DMA FSM state
  always @(posedge clock) begin
    if (r_dmaState == SET_UP_TRANS) begin
      beginTransactionOut <= `HI;
      readNotWriteOut     <= `HI;
      byteEnablesOut      <= BYTE_HI_ALL;
      burstSizeOut        <= s_usedBurstSize;
      addressDataOut      <= {r_busStartAddrShad[31:2], 2'd0};
    end else begin
      beginTransactionOut <= `LO;
      readNotWriteOut     <= `LO;
      byteEnablesOut      <= `LO_4;
      burstSizeOut        <= `LO_8;
      addressDataOut      <= `LO_32;
    end
  end

  //–––––––––––––––––––––––––––––––––––––––––––––––––––––––––––––––––––––––––––––––––––––––––––––––––––––––––––––––––––––
  //–––––––––––––––––––––––––––––––––––––––––––––––––––––––––––––––––––––––––––––––––––––––––––––––––––––––––––––––––––––
  //–––––––––––––––––––––––––––––––––––––––––––––––––––––––––––––––––––––––––––––––––––––––––––––––––––––––––––––––––––––
  // DMA FSM state and error register update
  always @(negedge clock) begin
    if (reset) begin
      r_dmaState <= IDLE;
      r_busError <= `LO;

    end else begin
      r_dmaState <= r_dmaNextState;

      if      (r_dmaState == INIT)     begin r_busError <= `LO; end 
      else if (r_dmaState == WAIT_END) begin r_busError <= `HI; end

    end
  end
  

  always @(posedge clock) begin
    case (r_dmaState)
      //0
      IDLE:         if      (s_requestDmaIn)      r_dmaNextState <= INIT;          //1
                    else                          r_dmaNextState <= IDLE;          //0
      //1
      INIT:                                       r_dmaNextState <= REQUEST_BUS;   //2
      //2
      REQUEST_BUS:  if      (transactionGranted)  r_dmaNextState <= SET_UP_TRANS;  //3
                    else                          r_dmaNextState <= REQUEST_BUS;   //2
      //3
      SET_UP_TRANS:                               r_dmaNextState <= DO_READ;       //4
      //4
      DO_READ:      if      (busErrorIn)          r_dmaNextState <= WAIT_END;      //5
                    else if (s_transCompleted)    r_dmaNextState <= IDLE;          //0
                    else if (r_endTransIn)        r_dmaNextState <= REQUEST_BUS;   //2
                    else                          r_dmaNextState <= DO_READ;
      //5
      WAIT_END:     if      (r_endTransIn)        r_dmaNextState <= IDLE;          //0
                    else                          r_dmaNextState <= WAIT_END;      //5

      default:                                    r_dmaNextState <= IDLE;          //0

    endcase
  end

  // Dual-ported SRAM instantiation
  // Port A: accessed by custom instruction interface, clocked by 'clock'
  // Port B: accessed by DMA bus interface, clocked by inverted 'clock'
  _mySSRAM #( .bitwidth(32),
              .nrOfEntries(512)) memory
            ( .clockA(clock),
              .clockB(~clock),
              .writeEnableA(s_isSramWrite), // Write enable for port A
              .writeEnableB(s_ramCiWriteEnable), // Write enable for port B
              .addressA(s_dmaAddrCI),       // Address for port A from custom instruction
              .addressB(r_ramCiAddr),     // Address for port B from DMA controller
              .dataInA(valueB),             // Data input for port A
              .dataInB(r_AddrDataIn),     // Data input for port B
              .dataOutA(s_sramDataValue),   // Data output from port A
              .dataOutB());                 // Data output from port B (unused)


endmodule

virtualprototype/modules/myMemory/verilog/myDmaRAM_tb.v
`timescale 1ns / 1ps

module myDmaRam_tb;

    reg clk = 0;
    reg reset = 1;
    reg start = 0;
    reg [31:0] valueA = 0;
    reg [31:0] valueB = 0;
    reg [7:0] ciN = 8'h14;
    reg transactionGranted = 0;
    reg endTransactionIn = 0;
    reg dataValidIn = 0;
    reg busErrorIn = 0;
    reg [31:0] addressDataIn = 32'h12345678;

    wire done;
    wire [31:0] result;
    wire requestTransaction;
    wire beginTransactionOut;
    wire readNotWriteOut;
    wire [3:0] byteEnablesOut;
    wire [7:0] burstSizeOut;
    wire [31:0] addressDataOut;

    always #5 clk = ~clk;

    myDmaRam dut (
        .start(start),
        .clock(clk),
        .reset(reset),
        .valueA(valueA),
        .valueB(valueB),
        .ciN(ciN),
        .done(done),
        .result(result),
        .requestTransaction(requestTransaction),
        .transactionGranted(transactionGranted),
        .endTransactionIn(endTransactionIn),
        .dataValidIn(dataValidIn),
        .busErrorIn(busErrorIn),
        .addressDataIn(addressDataIn),
        .beginTransactionOut(beginTransactionOut),
        .readNotWriteOut(readNotWriteOut),
        .byteEnablesOut(byteEnablesOut),
        .burstSizeOut(burstSizeOut),
        .addressDataOut(addressDataOut)
    );

    initial begin
        $dumpfile("dma.vcd");
        $dumpvars(0, myDmaRam_tb);

        #20 reset = 0;

        #10;
        valueA = (3'b001 << 10) | (1 << 9); //BUS_START_ADDR
        valueB = 32'h0000E000;
        start = 1; #10 start = 0;

        #20;
        valueA = (3'b010 << 10) | (1 << 9); //MEM_START_ADDR
        valueB = 32'h00000000;
        start = 1; #10 start = 0;

        // #20;
        // valueA = (3'b011 << 10) | (1 << 9); //BLOCK_SIZE
        // valueB = 32'd8;
        // start = 1; #10 start = 0;
        
        // #20;
        // valueA = (3'b100 << 10) | (1 << 9); //BURST_SIZE
        // valueB = 32'd7;
        // start = 1; #10 start = 0;
        
        #20;
        valueA = (3'b101 << 10) | (1 << 9); 
        valueB = 32'd1;
        start = 1; #20 start = 0;

        #50;
        wait(requestTransaction == 1);
        transactionGranted = 1; 
        #20 transactionGranted = 0;
        #20;

        dataValidIn = 1; endTransactionIn = 1; #10;
        dataValidIn = 0; endTransactionIn = 0;

        #100;
        $finish;
    end
endmodule

virtualprototype/modules/myMemory/verilog/dma.vcd
$date
	Sun May 25 01:36:33 2025
$end
$version
	Icarus Verilog
$end
$timescale
	1ps
$end
$scope module myDmaRam_tb $end
$var wire 32 ! result [31:0] $end
$var wire 1 " requestTransaction $end
$var wire 1 # readNotWriteOut $end
$var wire 1 $ done $end
$var wire 4 % byteEnablesOut [3:0] $end
$var wire 8 & burstSizeOut [7:0] $end
$var wire 1 ' beginTransactionOut $end
$var wire 32 ( addressDataOut [31:0] $end
$var reg 32 ) addressDataIn [31:0] $end
$var reg 1 * busErrorIn $end
$var reg 8 + ciN [7:0] $end
$var reg 1 , clk $end
$var reg 1 - dataValidIn $end
$var reg 1 . endTransactionIn $end
$var reg 1 / reset $end
$var reg 1 0 start $end
$var reg 1 1 transactionGranted $end
$var reg 32 2 valueA [31:0] $end
$var reg 32 3 valueB [31:0] $end
$scope module dut $end
$var wire 1 4 _controlBits $end
$var wire 32 5 addressDataIn [31:0] $end
$var wire 1 * busErrorIn $end
$var wire 8 6 ciN [7:0] $end
$var wire 1 , clock $end
$var wire 1 - dataValidIn $end
$var wire 1 $ done $end
$var wire 1 . endTransactionIn $end
$var wire 1 / reset $end
$var wire 32 7 result [31:0] $end
$var wire 1 8 s_dmaDone $end
$var wire 1 9 s_isMyCi $end
$var wire 1 : s_isSramWrite $end
$var wire 1 ; s_ramCiWriteEnable $end
$var wire 1 < s_requestDmaIn $end
$var wire 1 = s_transCompleted $end
$var wire 1 0 start $end
$var wire 1 1 transactionGranted $end
$var wire 32 > valueA [31:0] $end
$var wire 32 ? valueB [31:0] $end
$var wire 8 @ s_usedBurstSize [7:0] $end
$var wire 32 A s_sramDataValue [31:0] $end
$var wire 1 B s_dmaWrite $end
$var wire 1 C s_dmaIsAddrLO $end
$var wire 3 D s_dmaConfig [2:0] $end
$var wire 9 E s_dmaAddrCI [8:0] $end
$var wire 1 " requestTransaction $end
$var wire 8 F _restingBlockSize [7:0] $end
$var wire 8 G _maxBurstSize [7:0] $end
$var parameter 32 H ADDR_BYTE_INC $end
$var parameter 9 I ADDR_RAM_INC $end
$var parameter 3 J BLOCK_SIZE $end
$var parameter 3 K BURST_SIZE $end
$var parameter 3 L BUS_START_ADDR $end
$var parameter 4 M BYTE_HI_ALL $end
$var parameter 32 N CF_HI_B $end
$var parameter 32 O CF_LO_B $end
$var parameter 32 P DMA_HI_B $end
$var parameter 32 Q DMA_LO_B $end
$var parameter 3 R DO_READ $end
$var parameter 3 S IDLE $end
$var parameter 3 T INIT $end
$var parameter 3 U MEM_DATA $end
$var parameter 3 V MEM_START_ADDR $end
$var parameter 3 W REQUEST_BUS $end
$var parameter 3 X SET_UP_TRANS $end
$var parameter 10 Y SINGLE_BLOCK $end
$var parameter 2 Z START_BUS_TO_MEM $end
$var parameter 2 [ START_MEM_TO_BUT $end
$var parameter 3 \ STATUS_R $end
$var parameter 3 ] WAIT_END $end
$var parameter 32 ^ WRITE_B $end
$var parameter 8 _ customId $end
$var reg 32 ` addressDataOut [31:0] $end
$var reg 1 ' beginTransactionOut $end
$var reg 8 a burstSizeOut [7:0] $end
$var reg 4 b byteEnablesOut [3:0] $end
$var reg 32 c r_AddrDataIn [31:0] $end
$var reg 32 d r_blockSize [31:0] $end
$var reg 10 e r_blockSizeShad [9:0] $end
$var reg 1 f r_busError $end
$var reg 32 g r_busStartAddr [31:0] $end
$var reg 32 h r_busStartAddrShad [31:0] $end
$var reg 1 i r_dataValidIn $end
$var reg 3 j r_dmaNextState [2:0] $end
$var reg 3 k r_dmaState [2:0] $end
$var reg 1 l r_endTransIn $end
$var reg 1 m r_isSramRead $end
$var reg 32 n r_memoryStartAddr [31:0] $end
$var reg 9 o r_ramCiAddr [8:0] $end
$var reg 32 p r_result [31:0] $end
$var reg 32 q r_usedBurstSize [31:0] $end
$var reg 1 # readNotWriteOut $end
$scope module memory $end
$var wire 9 r addressA [8:0] $end
$var wire 9 s addressB [8:0] $end
$var wire 1 , clockA $end
$var wire 1 t clockB $end
$var wire 32 u dataInA [31:0] $end
$var wire 32 v dataInB [31:0] $end
$var wire 1 : writeEnableA $end
$var wire 1 ; writeEnableB $end
$var parameter 32 w bitwidth $end
$var parameter 32 x nrOfEntries $end
$var reg 32 y dataOutA [31:0] $end
$var reg 32 z dataOutB [31:0] $end
$upscope $end
$upscope $end
$upscope $end
$enddefinitions $end
$comment Show the parameter values. $end
$dumpall
b1000000000 x
b100000 w
b10100 _
b1001 ^
b101 ]
b101 \
b10 [
b1 Z
b1 Y
b11 X
b10 W
b10 V
b0 U
b1 T
b0 S
b100 R
b0 Q
b1 P
b1010 O
b1100 N
b1111 M
b1 L
b100 K
b11 J
b1 I
b100 H
$end
#0
$dumpvars
bx z
bx y
bx v
b0 u
1t
bx s
b0 r
bx q
b0 p
bx o
bx n
xm
xl
b0 k
bx j
xi
bx h
bx g
0f
bx e
bx d
bx c
bx b
bx a
bx `
bx G
bx F
b0 E
b0 D
1C
0B
bx A
bx @
b0 ?
b0 >
x=
0<
0;
0:
09
x8
b0 7
b10100 6
b10010001101000101011001111000 5
04
b0 3
b0 2
01
00
1/
0.
0-
0,
b10100 +
0*
b10010001101000101011001111000 )
bx (
x'
bx &
bx %
x$
x#
0"
b0 !
$end
#5000
b1 G
0$
0=
0m
b0 q
b0 d
b0 n
b0 g
b10010001101000101011001111000 c
b10010001101000101011001111000 v
0i
0l
b0 (
b0 `
b0 &
b0 a
b0 %
b0 b
0#
0'
b0 j
0t
1,
#10000
1t
0,
#15000
b11111111 @
b11111111 F
18
b0 o
b0 s
b0 e
b0 h
0t
1,
#20000
1t
0,
0/
#25000
0t
1,
#30000
1:
1$
1t
19
b1 D
1B
0,
10
b1110000000000000 3
b1110000000000000 ?
b1110000000000000 u
b11000000000 2
b11000000000 >
#35000
b1110000000000000 g
0t
1,
#40000
b1110000000000000 z
0:
0$
1t
09
0,
00
#45000
b1110000000000000 A
b1110000000000000 y
b1110000000000000 h
0t
1,
#50000
1t
0,
#55000
0t
1,
#60000
1:
1$
1t
19
b10 D
0,
10
b0 3
b0 ?
b0 u
b101000000000 2
b101000000000 >
#65000
0t
1,
#70000
b0 z
0:
0$
1t
09
0,
00
#75000
b0 A
b0 y
0t
1,
#80000
1t
0,
#85000
0t
1,
#90000
1:
1$
1<
14
1t
19
b101 D
0,
10
b1 3
b1 ?
b1 u
b1011000000000 2
b1011000000000 >
#95000
b1 j
0t
1,
#100000
b1 z
b1 k
1t
0,
#105000
b1 A
b1 y
b10 j
0t
1,
#110000
1"
b10 k
0<
0:
0$
1t
09
0,
00
#115000
0t
1,
#120000
1t
0,
#125000
0t
1,
#130000
1t
0,
#135000
0t
1,
#140000
1t
0,
#145000
0t
1,
#150000
1t
0,
#155000
0t
1,
#160000
1t
0,
11
#165000
b11 j
0t
1,
#170000
0"
b11 k
1t
0,
#175000
b100 j
b1110000000000000 (
b1110000000000000 `
b11111111 &
b11111111 a
b1111 %
b1111 b
1#
1'
0t
1,
#180000
b100 k
1t
0,
01
#185000
b0 (
b0 `
b0 &
b0 a
b0 %
b0 b
0#
0'
0t
1,
#190000
1t
0,
#195000
0t
1,
#200000
1t
0,
1.
1-
#205000
1;
1=
1i
1l
0t
1,
#210000
1t
0,
0.
0-
#215000
b11111110 F
b0 @
08
0;
0=
b0 j
b1 o
b1 s
b1111111111 e
b1110000000000100 h
0i
0l
b10010001101000101011001111000 A
b10010001101000101011001111000 y
0t
1,
#220000
bx z
b0 k
1t
0,
#225000
b11111111 F
b11111111 @
18
b0 o
b0 s
b0 e
b1110000000000000 h
0t
1,
#230000
b10010001101000101011001111000 z
1t
0,
